LICENSE
MANIFEST.in
README.md
pyproject.toml
setup.py
helpers/__init__.py
helpers/identify_xspec.py
helpers/report_xspec_version.cxx
helpers/template.py
src/xspex.cpp
src/include/xspex.hpp
src/xspex/__init__.py
src/xspex/primitive.py
src/xspex.egg-info/PKG-INFO
src/xspex.egg-info/SOURCES.txt
src/xspex.egg-info/dependency_links.txt
src/xspex.egg-info/requires.txt
src/xspex.egg-info/top_level.txt
template/__init__.py
template/xspex.cpp
tests/test_basic.py
tests/test_primitive.py