Metadata-Version: 2.4
Name: xspex
Version: 0.0.7
Summary: Access Xspec models and corresponding JAX/XLA ops.
Author-email: Wang-Chen Xue <wcxuemail@gmail.com>
License-Expression: GPL-3.0-or-later
Project-URL: Documentation, https://github.com/wcxve/xspex#readme
Project-URL: Issues, https://github.com/wcxve/xspex/issues
Project-URL: Source, https://github.com/wcxve/xspex
Classifier: Intended Audience :: Science/Research
Classifier: Operating System :: POSIX
Classifier: Programming Language :: C
Classifier: Programming Language :: Python :: 3.9
Classifier: Programming Language :: Python :: 3.10
Classifier: Programming Language :: Python :: 3.11
Classifier: Programming Language :: Python :: 3.12
Requires-Python: <3.13,>=3.9
License-File: LICENSE
Requires-Dist: numpy>=1.23.3
Requires-Dist: jax<=0.6.0,>=0.4.16
Requires-Dist: jaxlib<=0.6.0,>=0.4.16
Provides-Extra: test
Requires-Dist: coverage[toml]; extra == "test"
Requires-Dist: pytest; extra == "test"
Requires-Dist: pytest-cov; extra == "test"
Requires-Dist: pytest-xdist; extra == "test"
Dynamic: license-file
